[
    {
        "arguments": [
            "gcc",
            "-c",
            "-DHAVE_CONFIG_H",
            "-I.",
            "-I..",
            "-I..",
            "-I../src",
            "-Wdate-time",
            "-D_FORTIFY_SOURCE=2",
            "-W",
            "-Wall",
            "-Wshadow",
            "-Wformat",
            "-Wundef",
            "-D_GNU_SOURCE",
            "-g",
            "-O2",
            "-fdebug-prefix-map=/home/acanino/dep-trace/vlc-src-out/libcap-ng0.original/libcap-ng-0.7.9=.",
            "-fstack-protector-strong",
            "-Wformat",
            "-Werror=format-security",
            "-o",
            "pscap.o",
            "pscap.c"
        ],
        "directory": "/home/acanino/dep-trace/vlc-src-out/libcap-ng0.original/libcap-ng-0.7.9/utils",
        "file": "pscap.c"
    },
    {
        "arguments": [
            "gcc",
            "-c",
            "-DHAVE_CONFIG_H",
            "-I.",
            "-I..",
            "-I.",
            "-I..",
            "-Wdate-time",
            "-D_FORTIFY_SOURCE=2",
            "-fPIC",
            "-DPIC",
            "-W",
            "-Wall",
            "-Wshadow",
            "-Wformat",
            "-Wundef",
            "-D_GNU_SOURCE",
            "-g",
            "-O2",
            "-fdebug-prefix-map=/home/acanino/dep-trace/vlc-src-out/libcap-ng0.original/libcap-ng-0.7.9=.",
            "-fstack-protector-strong",
            "-Wformat",
            "-Werror=format-security",
            "-o",
            "lookup_table.o",
            "lookup_table.c"
        ],
        "directory": "/home/acanino/dep-trace/vlc-src-out/libcap-ng0.original/libcap-ng-0.7.9/src",
        "file": "lookup_table.c"
    },
    {
        "arguments": [
            "gcc",
            "-c",
            "-DHAVE_CONFIG_H",
            "-I.",
            "-I..",
            "-I..",
            "-I../src",
            "-Wdate-time",
            "-D_FORTIFY_SOURCE=2",
            "-W",
            "-Wall",
            "-Wshadow",
            "-Wformat",
            "-Wundef",
            "-D_GNU_SOURCE",
            "-g",
            "-O2",
            "-fdebug-prefix-map=/home/acanino/dep-trace/vlc-src-out/libcap-ng0.original/libcap-ng-0.7.9=.",
            "-fstack-protector-strong",
            "-Wformat",
            "-Werror=format-security",
            "-o",
            "captest.o",
            "captest.c"
        ],
        "directory": "/home/acanino/dep-trace/vlc-src-out/libcap-ng0.original/libcap-ng-0.7.9/utils",
        "file": "captest.c"
    },
    {
        "arguments": [
            "gcc",
            "-c",
            "-DHAVE_CONFIG_H",
            "-I.",
            "-I..",
            "-I.",
            "-I..",
            "-Wdate-time",
            "-D_FORTIFY_SOURCE=2",
            "-fPIC",
            "-DPIC",
            "-W",
            "-Wall",
            "-Wshadow",
            "-Wformat",
            "-Wundef",
            "-D_GNU_SOURCE",
            "-g",
            "-O2",
            "-fdebug-prefix-map=/home/acanino/dep-trace/vlc-src-out/libcap-ng0.original/libcap-ng-0.7.9=.",
            "-fstack-protector-strong",
            "-Wformat",
            "-Werror=format-security",
            "-fPIC",
            "-DPIC",
            "-o",
            ".libs/cap-ng.o",
            "cap-ng.c"
        ],
        "directory": "/home/acanino/dep-trace/vlc-src-out/libcap-ng0.original/libcap-ng-0.7.9/src",
        "file": "cap-ng.c"
    },
    {
        "arguments": [
            "gcc",
            "-c",
            "-DHAVE_CONFIG_H",
            "-I.",
            "-I..",
            "-I..",
            "-I../src",
            "-Wdate-time",
            "-D_FORTIFY_SOURCE=2",
            "-W",
            "-Wall",
            "-Wshadow",
            "-Wformat",
            "-Wundef",
            "-D_GNU_SOURCE",
            "-g",
            "-O2",
            "-fdebug-prefix-map=/home/acanino/dep-trace/vlc-src-out/libcap-ng0.original/libcap-ng-0.7.9=.",
            "-fstack-protector-strong",
            "-Wformat",
            "-Werror=format-security",
            "-o",
            "proc-llist.o",
            "proc-llist.c"
        ],
        "directory": "/home/acanino/dep-trace/vlc-src-out/libcap-ng0.original/libcap-ng-0.7.9/utils",
        "file": "proc-llist.c"
    },
    {
        "arguments": [
            "gcc",
            "-c",
            "-DHAVE_CONFIG_H",
            "-I.",
            "-I..",
            "-I.",
            "-I..",
            "-Wdate-time",
            "-D_FORTIFY_SOURCE=2",
            "-fPIC",
            "-DPIC",
            "-W",
            "-Wall",
            "-Wshadow",
            "-Wformat",
            "-Wundef",
            "-D_GNU_SOURCE",
            "-g",
            "-O2",
            "-fdebug-prefix-map=/home/acanino/dep-trace/vlc-src-out/libcap-ng0.original/libcap-ng-0.7.9=.",
            "-fstack-protector-strong",
            "-Wformat",
            "-Werror=format-security",
            "-o",
            "cap-ng.o",
            "cap-ng.c"
        ],
        "directory": "/home/acanino/dep-trace/vlc-src-out/libcap-ng0.original/libcap-ng-0.7.9/src",
        "file": "cap-ng.c"
    },
    {
        "arguments": [
            "gcc",
            "-c",
            "-DHAVE_CONFIG_H",
            "-I.",
            "-I..",
            "-I..",
            "-I../src",
            "-Wdate-time",
            "-D_FORTIFY_SOURCE=2",
            "-W",
            "-Wall",
            "-Wshadow",
            "-Wformat",
            "-Wundef",
            "-D_GNU_SOURCE",
            "-g",
            "-O2",
            "-fdebug-prefix-map=/home/acanino/dep-trace/vlc-src-out/libcap-ng0.original/libcap-ng-0.7.9=.",
            "-fstack-protector-strong",
            "-Wformat",
            "-Werror=format-security",
            "-o",
            "netcap.o",
            "netcap.c"
        ],
        "directory": "/home/acanino/dep-trace/vlc-src-out/libcap-ng0.original/libcap-ng-0.7.9/utils",
        "file": "netcap.c"
    },
    {
        "arguments": [
            "gcc",
            "-c",
            "-DHAVE_CONFIG_H",
            "-I.",
            "-I..",
            "-I..",
            "-I../src",
            "-Wdate-time",
            "-D_FORTIFY_SOURCE=2",
            "-W",
            "-Wall",
            "-Wshadow",
            "-Wformat",
            "-Wundef",
            "-D_GNU_SOURCE",
            "-g",
            "-O2",
            "-fdebug-prefix-map=/home/acanino/dep-trace/vlc-src-out/libcap-ng0.original/libcap-ng-0.7.9=.",
            "-fstack-protector-strong",
            "-Wformat",
            "-Werror=format-security",
            "-o",
            "filecap.o",
            "filecap.c"
        ],
        "directory": "/home/acanino/dep-trace/vlc-src-out/libcap-ng0.original/libcap-ng-0.7.9/utils",
        "file": "filecap.c"
    },
    {
        "arguments": [
            "gcc",
            "-c",
            "-DHAVE_CONFIG_H",
            "-I.",
            "-I../..",
            "-I.",
            "-I../..",
            "-I/usr/include/python2.7",
            "-Wdate-time",
            "-D_FORTIFY_SOURCE=2",
            "-g",
            "-O2",
            "-fdebug-prefix-map=/home/acanino/dep-trace/vlc-src-out/libcap-ng0.original/libcap-ng-0.7.9=.",
            "-fstack-protector-strong",
            "-Wformat",
            "-Werror=format-security",
            "-fPIC",
            "-DPIC",
            "-o",
            ".libs/_capng_la-capng_wrap.o",
            "capng_wrap.c"
        ],
        "directory": "/home/acanino/dep-trace/vlc-src-out/libcap-ng0.original/libcap-ng-0.7.9/bindings/python",
        "file": "capng_wrap.c"
    },
    {
        "arguments": [
            "gcc",
            "-c",
            "-DHAVE_CONFIG_H",
            "-I.",
            "-I../..",
            "-I.",
            "-I../..",
            "-I/usr/include/python3.7m",
            "-I/usr/include/python3.7m",
            "-Wdate-time",
            "-D_FORTIFY_SOURCE=2",
            "-g",
            "-O2",
            "-fdebug-prefix-map=/home/acanino/dep-trace/vlc-src-out/libcap-ng0.original/libcap-ng-0.7.9=.",
            "-fstack-protector-strong",
            "-Wformat",
            "-Werror=format-security",
            "-fPIC",
            "-DPIC",
            "-o",
            ".libs/_capng_la-capng_wrap.o",
            "capng_wrap.c"
        ],
        "directory": "/home/acanino/dep-trace/vlc-src-out/libcap-ng0.original/libcap-ng-0.7.9/bindings/python3",
        "file": "capng_wrap.c"
    },
    {
        "arguments": [
            "gcc",
            "-c",
            "-DHAVE_CONFIG_H",
            "-I.",
            "-I..",
            "-I.",
            "-I..",
            "-Wdate-time",
            "-D_FORTIFY_SOURCE=2",
            "-fPIC",
            "-DPIC",
            "-W",
            "-Wall",
            "-Wshadow",
            "-Wformat",
            "-Wundef",
            "-D_GNU_SOURCE",
            "-g",
            "-O2",
            "-fdebug-prefix-map=/home/acanino/dep-trace/vlc-src-out/libcap-ng0.original/libcap-ng-0.7.9=.",
            "-fstack-protector-strong",
            "-Wformat",
            "-Werror=format-security",
            "-fPIC",
            "-DPIC",
            "-o",
            ".libs/lookup_table.o",
            "lookup_table.c"
        ],
        "directory": "/home/acanino/dep-trace/vlc-src-out/libcap-ng0.original/libcap-ng-0.7.9/src",
        "file": "lookup_table.c"
    }
]